react_bridge/__init__.py
react_bridge/apps.py
react_bridge/config.py
react_bridge/context_processors.py
react_bridge/utils.py
react_bridge/jsbundler/.gitignore
react_bridge/jsbundler/bridge.js
react_bridge/jsbundler/webpack.common.js
react_bridge/jsbundler/webpack.dev.js
react_bridge/jsbundler/webpack.prod.js
react_bridge/management/commands/jsbuild.py
react_bridge/management/commands/jsdevserver.py
react_bridge/management/commands/jsinit.py
react_bridge/migrations/__init__.py
react_bridge/starter_js/.eslintrc.json
react_bridge/starter_js/.gitignore
react_bridge/starter_js/package.json
react_bridge/starter_js/src/MyComponent.css
react_bridge/starter_js/src/MyComponent.js
react_bridge/starter_js/src/index.js
react_bridge/templatetags/__init__.py
react_bridge/templatetags/react_bridge.py
django_react_bridge-0.2.0.dist-info/LICENSE
django_react_bridge-0.2.0.dist-info/METADATA
django_react_bridge-0.2.0.dist-info/WHEEL
django_react_bridge-0.2.0.dist-info/top_level.txt
django_react_bridge-0.2.0.dist-info/RECORD
