Metadata-Version: 2.1
Name: django-react-bridge
Version: 0.2.0
Summary: A React bridge for Django
Home-page: https://github.com/inmagik/django-react-bridge
Author: Giovanni Fumagalli
Author-email: giovanni.fumagalli@inmagik.com
License: UNKNOWN
Platform: UNKNOWN
Classifier: Programming Language :: Python :: 3
Classifier: License :: OSI Approved :: MIT License
Classifier: Operating System :: OS Independent
Requires-Python: >=3.6
Requires-Dist: requests (<3,>=2)
